README.rst
setup.py
smartmob_agent/__init__.py
smartmob_agent/version.txt
smartmob_agent.egg-info/PKG-INFO
smartmob_agent.egg-info/SOURCES.txt
smartmob_agent.egg-info/dependency_links.txt
smartmob_agent.egg-info/entry_points.txt
smartmob_agent.egg-info/requires.txt
smartmob_agent.egg-info/top_level.txt