Metadata-Version: 1.1
Name: smartmob-agent
Version: 0.3.0
Summary: Remote Procfile runner
Home-page: https://github.com/smartmob-project/smartmob-agent
Author: Andre Caron
Author-email: ac@smartmob.org
License: MIT
Keywords: procfile asyncio
Platform: UNKNOWN
Classifier: Development Status :: 1 - Planning
Classifier: Intended Audience :: Developers
Classifier: License :: OSI Approved :: MIT License
Classifier: Operating System :: MacOS :: MacOS X
Classifier: Programming Language :: Python
Classifier: Programming Language :: Python :: 3.5
Classifier: Topic :: Software Development :: Libraries
